extension/include/osqputilspy.h
extension/include/osqpobjectpy.h
extension/include/osqpworkspacepy.h
extension/include/osqpresultspy.h
extension/include/osqpinfopy.h
extension/include/osqpmodulemethods.h
extension/src/osqpmodule.c
extension/src/libosqp.a
extension/src/.gitignore
osqppurepy/interface.py
osqppurepy/_osqp.py
osqppurepy/__init__.py
osqp/_osqp.cpython-311-darwin.so
osqp/_version.py
osqp/interface.py
osqp/__init__.py
osqp/utils.py
osqp/tests/mkl_pardiso_test.py
osqp/tests/warm_start_test.py
osqp/tests/polishing_test.py
osqp/tests/derivative_test.py
osqp/tests/codegen_matrices_test.py
osqp/tests/update_matrices_test.py
osqp/tests/primal_infeasibility_test.py
osqp/tests/codegen_vectors_test.py
osqp/tests/utils.py
osqp/tests/non_convex_test.py
osqp/tests/unconstrained_test.py
osqp/tests/dual_infeasibility_test.py
osqp/tests/basic_test.py
osqp/tests/feasibility_test.py
osqp/tests/multithread_test.py
osqp/tests/solutions/test_update_P_A_indA.npz
osqp/tests/solutions/test_update_P_A_indP_indA.npz
osqp/tests/solutions/test_update_q.npz
osqp/tests/solutions/test_update_P.npz
osqp/tests/solutions/test_update_P_A_indP.npz
osqp/tests/solutions/test_update_u.npz
osqp/tests/solutions/test_update_A.npz
osqp/tests/solutions/test_feasibility_problem.npz
osqp/tests/solutions/test_basic_QP.npz
osqp/tests/solutions/__init__.py
osqp/tests/solutions/test_update_P_A_allind.npz
osqp/tests/solutions/test_polish_unconstrained.npz
osqp/tests/solutions/test_update_P_allind.npz
osqp/tests/solutions/test_update_l.npz
osqp/tests/solutions/test_solve.npz
osqp/tests/solutions/test_update_bounds.npz
osqp/tests/solutions/test_polish_random.npz
osqp/tests/solutions/test_polish_simple.npz
osqp/tests/solutions/test_unconstrained_problem.npz
osqp/tests/solutions/test_update_A_allind.npz
osqp/codegen/__init__.py
osqp/codegen/.gitignore
osqp/codegen/utils.py
osqp/codegen/code_generator.py
osqp-0.6.7.post3.dist-info/RECORD
osqp-0.6.7.post3.dist-info/LICENSE
osqp-0.6.7.post3.dist-info/WHEEL
osqp-0.6.7.post3.dist-info/top_level.txt
osqp-0.6.7.post3.dist-info/METADATA
