Metadata-Version: 2.1
Name: osqp
Version: 0.6.7.post3
Summary: OSQP: The Operator Splitting QP Solver
Home-page: https://osqp.org/
Author: Goran Banjac
Author-email: Bartolomeo Stellato <bartolomeo.stellato@gmail.com>
Classifier: License :: OSI Approved :: Apache Software License
License-File: LICENSE
Requires-Dist: numpy >=1.7
Requires-Dist: scipy >=0.13.2
Requires-Dist: qdldl
Provides-Extra: dev
Requires-Dist: scipy !=1.12.0 ; extra == 'dev'
